mlops_feature/__init__.py
mlops_feature/etl/__init__.py
mlops_feature/etl/cleaning.py
mlops_feature/etl/extract.py
mlops_feature/etl/load.py
mlops_feature/etl/validation.py
mlops_feature/feature_view.py
mlops_feature/pipeline.py
mlops_feature/settings.py
mlops_feature/utils.py
mlops_feature_pipeline-0.3.0.dist-info/METADATA
mlops_feature_pipeline-0.3.0.dist-info/WHEEL
mlops_feature_pipeline-0.3.0.dist-info/RECORD
