Metadata-Version: 2.1
Name: mlops_feature_pipeline
Version: 0.3.0
Summary: 
Author: CryLake
Author-email: minhchauss123456@gmail.com
Requires-Python: >=3.10,<3.11
Classifier: Programming Language :: Python :: 3
Classifier: Programming Language :: Python :: 3.10
Requires-Dist: fire (>=0.5.0,<0.6.0)
Requires-Dist: hopsworks (==3.2.0)
Requires-Dist: pandas (>=1.3.5)
Requires-Dist: python-dotenv (>=0.21.1)
Requires-Dist: requests (>=2.28.2,<3.0.0)
Requires-Dist: yarl (>=1.8.2,<2.0.0)
